twat_genai/__init__.py
twat_genai/__main__.py
twat_genai/__main___loras.json
twat_genai/__version__.py
twat_genai/cli.py
twat_genai/core/config.py
twat_genai/core/image.py
twat_genai/core/models.py
twat_genai/core/prompt.py
twat_genai/engines/base.py
twat_genai/engines/fal/__init__.py
twat_genai/engines/fal/client.py
twat_genai/engines/fal/config.py
twat_genai/engines/fal/lora.py
twat_genai/engines/fal/models.py
twat_genai-2.7.5.dist-info/METADATA
twat_genai-2.7.5.dist-info/WHEEL
twat_genai-2.7.5.dist-info/entry_points.txt
twat_genai-2.7.5.dist-info/licenses/LICENSE
twat_genai-2.7.5.dist-info/RECORD
