Metadata-Version: 2.4
Name: twat-genai
Version: 2.7.5
Project-URL: Documentation, https://github.com/twardoch/twat-genai#readme
Project-URL: Issues, https://github.com/twardoch/twat-genai/issues
Project-URL: Source, https://github.com/twardoch/twat-genai
Author-email: Adam Twardoch <adam+github@twardoch.com>
License-Expression: MIT
License-File: LICENSE
Classifier: Development Status :: 4 - Beta
Classifier: Programming Language :: Python
Classifier: Programming Language :: Python :: 3.10
Classifier: Programming Language :: Python :: 3.11
Classifier: Programming Language :: Python :: 3.12
Classifier: Programming Language :: Python :: Implementation :: CPython
Classifier: Programming Language :: Python :: Implementation :: PyPy
Requires-Python: >=3.10
Requires-Dist: fal-client>=0.5.9
Requires-Dist: httpx>=0.28.1
Requires-Dist: numpy>=2.2.3
Requires-Dist: pillow>=11.1.0
Requires-Dist: pydantic>=2.10.6
Requires-Dist: python-slugify>=8.0.4
Requires-Dist: twat-image>=1.8.1
Requires-Dist: twat>=1.8.1
Requires-Dist: webcolors>=24.11.1
Provides-Extra: all
Requires-Dist: fal-client>=0.5.9; extra == 'all'
Requires-Dist: httpx>=0.28.1; extra == 'all'
Requires-Dist: numpy>=2.2.3; extra == 'all'
Requires-Dist: pillow>=11.1.0; extra == 'all'
Requires-Dist: pydantic>=2.10.6; extra == 'all'
Requires-Dist: python-slugify>=8.0.4; extra == 'all'
Requires-Dist: twat-image>=1.8.1; extra == 'all'
Requires-Dist: twat>=1.8.1; extra == 'all'
Requires-Dist: webcolors>=24.11.1; extra == 'all'
Provides-Extra: dev
Requires-Dist: mypy>=1.15.0; extra == 'dev'
Requires-Dist: pre-commit>=4.1.0; extra == 'dev'
Requires-Dist: ruff>=0.9.6; extra == 'dev'
Provides-Extra: test
Requires-Dist: pytest-benchmark[histogram]>=5.1.0; extra == 'test'
Requires-Dist: pytest-cov>=6.0.0; extra == 'test'
Requires-Dist: pytest-xdist>=3.6.1; extra == 'test'
Requires-Dist: pytest>=8.3.4; extra == 'test'
